{
    "length": 5.6,
    "dialogue_id": 201000338,
    "wait_user_click_at_end": true,
    "play_dialogue_sound_when_show_ui_if_no_say_action": true,
    "play_dialogue_sound_when_say_action_without_data": true,
    "black_switch_in": false,
    "cached_dialogue_npc_id": 490060,
    "actions": [
        {
            "ClassPath": "NewRoco.Modules.System.Dialogue.Action.Timeline.DialogueTimelineShowUIEvent",
            "Name": "\u663e\u793a\u5bf9\u8bddUI",
            "OwnerActorID": -100,
            "StartTime": 0.0
        },
        {
            "ClassPath": "NewRoco.Modules.System.Dialogue.Action.Timeline.DialogueTimelineNPCSetLocationEvent",
            "Name": "\u8bbe\u7f6e\u4f4d\u7f6e",
            "OwnerActorID": -1,
            "StartTime": 0.0,
            "TargetLocation": {
                "X": 895.5,
                "Y": -86.6,
                "Z": 86.9
            },
            "TargetRotation": {
                "Pitch": 0.0,
                "Yaw": 176.7,
                "Roll": 0.0
            },
            "ReportLocation": false
        },
        {
            "ClassPath": "NewRoco.Modules.System.Dialogue.Action.Timeline.DialogueTimelineNPCActorAnimAction",
            "Name": "\u52a8\u4f5c",
            "OwnerActorID": 19235,
            "StartTime": 0.0,
            "EndTime": 2.2,
            "MinimalDuration": 0.1,
            "Action": "happy2",
            "BlendInTime": 0.5,
            "BlendOutTime": 1.0,
            "LoopCount": 1,
            "StartPoint": 0.0,
            "EndPoint": 0.0,
            "StopAnimAtEnd": false
        },
        {
            "ClassPath": "NewRoco.Modules.System.Dialogue.Action.Timeline.DialogueTimelineCameraSetupEvent_FreeCamera",
            "Name": "\u81ea\u7531\u955c\u5934",
            "OwnerActorID": -101,
            "StartTime": 0.0,
            "EndTime": 1.0,
            "MinimalDuration": 0.1,
            "BlendType": 1,
            "BlendExp": 1.0,
            "TargetActorID": -6,
            "RelativeLocation": {
                "X": 479.7,
                "Y": -394.3,
                "Z": 113.6
            },
            "RelativeRotation": {
                "Pitch": 2.8,
                "Yaw": 137.1,
                "Roll": 0.0
            },
            "FOV": 50.0
        },
        {
            "ClassPath": "NewRoco.Modules.System.Dialogue.Action.Timeline.DialogueTimelineCameraMoveState_Parallel",
            "Name": "\u5e73\u79fb\u8fd0\u955c",
            "OwnerActorID": -101,
            "StartTime": 0.0,
            "EndTime": 8.3,
            "MinimalDuration": 0.1,
            "MoveDistance": 120.0,
            "MoveDirection": 0
        },
        {
            "ClassPath": "NewRoco.Modules.System.Dialogue.Action.Timeline.DialogueTimelineNPCActorAnimAction",
            "Name": "\u52a8\u4f5c",
            "OwnerActorID": 19235,
            "StartTime": 2.8,
            "EndTime": 5.6,
            "MinimalDuration": 0.1,
            "Action": "dialogue1",
            "BlendInTime": 0.2,
            "BlendOutTime": 1.0,
            "LoopCount": 1,
            "StartPoint": 0.0,
            "EndPoint": 0.0,
            "StopAnimAtEnd": false
        }
    ]
}