{
    "length": 10.82,
    "dialogue_id": 201010350,
    "wait_user_click_at_end": true,
    "play_dialogue_sound_when_show_ui_if_no_say_action": true,
    "play_dialogue_sound_when_say_action_without_data": true,
    "black_switch_in": true,
    "cached_dialogue_npc_id": 33315,
    "actions": [
        {
            "ClassPath": "NewRoco.Modules.System.Dialogue.Action.Timeline.DialogueTimelineShowUIEvent",
            "Name": "\u663e\u793a\u5bf9\u8bddUI",
            "OwnerActorID": -100,
            "StartTime": 0.0
        },
        {
            "ClassPath": "NewRoco.Modules.System.Dialogue.Action.Timeline.DialogueTimelineNPCSayState",
            "Name": "\u89d2\u8272\u8bf4\u8bdd",
            "OwnerActorID": 0,
            "StartTime": 0.0,
            "EndTime": 1.0,
            "MinimalDuration": 0.1,
            "SoundFileName": "dialog201010350",
            "PlayFacialAnim": true
        },
        {
            "ClassPath": "NewRoco.Modules.System.Dialogue.Action.Timeline.DialogueTimelineNPCSetupAction",
            "Name": "\u671d\u5411",
            "OwnerActorID": 33315,
            "StartTime": 1.6,
            "BodyTargetActorID": 0,
            "BodyTurnTo": 0.0,
            "BodyTurnSpeedScale": 1.0,
            "HeadTargetActorID": -1,
            "HeadTurnTo": 0.0,
            "HeadTurnToY": 0.0,
            "HeadTurnSpeedScale": 1.0,
            "EyeTargetActorID": 0,
            "EyeTurnToHorizontal": 0.0,
            "EyeTurnToVertical": 0.0,
            "EyeTurnSpeedScale": 1.0
        },
        {
            "ClassPath": "NewRoco.Modules.System.Dialogue.Action.Timeline.DialogueTimelineNPCSetLocationEvent",
            "Name": "\u8bbe\u7f6e\u4f4d\u7f6e",
            "OwnerActorID": -1,
            "StartTime": 0.0,
            "TargetLocation": {
                "X": 263.6,
                "Y": -54.7,
                "Z": 1.8,
                "Base": "Mesh"
            },
            "TargetRotation": {
                "Pitch": 0.0,
                "Yaw": 162.0,
                "Roll": 0.0
            },
            "ReportLocation": false
        },
        {
            "ClassPath": "NewRoco.Modules.System.Dialogue.Action.Timeline.DialogueTimelineNPCSetLocationEvent",
            "Name": "\u8bbe\u7f6e\u4f4d\u7f6e",
            "OwnerActorID": 35057,
            "StartTime": 0.0,
            "TargetLocation": {
                "X": 26.0,
                "Y": -103.0,
                "Z": -2.6,
                "Base": "Mesh"
            },
            "TargetRotation": {
                "Pitch": 0.0,
                "Yaw": 51.1,
                "Roll": 0.0
            },
            "ReportLocation": false
        },
        {
            "ClassPath": "NewRoco.Modules.System.Dialogue.Action.Timeline.DialogueTimelineNPCSetupAction",
            "Name": "\u671d\u5411",
            "OwnerActorID": 35057,
            "StartTime": 0.0,
            "BodyTargetActorID": 0,
            "BodyTurnTo": 0.0,
            "BodyTurnSpeedScale": 1.0,
            "HeadTargetActorID": -1,
            "HeadTurnTo": 0.0,
            "HeadTurnToY": 0.0,
            "HeadTurnSpeedScale": 1.0,
            "EyeTargetActorID": 0,
            "EyeTurnToHorizontal": 0.0,
            "EyeTurnToVertical": 0.0,
            "EyeTurnSpeedScale": 1.0
        },
        {
            "ClassPath": "NewRoco.Modules.System.Dialogue.Action.Timeline.DialogueTimelineNPCActorAnimAction",
            "Name": "\u52a8\u4f5c",
            "OwnerActorID": 35057,
            "StartTime": 0.0,
            "EndTime": 2.0,
            "MinimalDuration": 0.1,
            "Action": "Happy2",
            "BlendInTime": 0.0,
            "BlendOutTime": 0.0,
            "LoopCount": 1,
            "StartPoint": 0.0,
            "EndPoint": 0.0,
            "StopAnimAtEnd": false,
            "Rate": 1
        },
        {
            "ClassPath": "NewRoco.Modules.System.Dialogue.Action.Timeline.DialogueTimelineNPCActorAnimAction",
            "Name": "\u52a8\u4f5c",
            "OwnerActorID": 33315,
            "StartTime": 2.0,
            "EndTime": 4.333333253860474,
            "MinimalDuration": 0.1,
            "Action": "Happy2",
            "BlendInTime": 0.5,
            "BlendOutTime": 0.0,
            "LoopCount": 1,
            "StartPoint": 0.0,
            "EndPoint": 0.0,
            "StopAnimAtEnd": false
        },
        {
            "ClassPath": "NewRoco.Modules.System.Dialogue.Action.Timeline.DialogueTimelineCameraSetupEvent_FreeCamera",
            "Name": "\u81ea\u7531\u955c\u5934",
            "OwnerActorID": -101,
            "StartTime": 0.0,
            "EndTime": 3.0,
            "MinimalDuration": 0.1,
            "BlendType": 1,
            "BlendExp": 1.0,
            "TargetActorID": -6,
            "RelativeLocation": {
                "X": 357.1,
                "Y": 25.1,
                "Z": 142.1
            },
            "RelativeRotation": {
                "Pitch": 0.0,
                "Yaw": -162.0,
                "Roll": 0.0
            },
            "FOV": 45.0
        },
        {
            "ClassPath": "NewRoco.Modules.System.Dialogue.Action.Timeline.DialogueTimelineNPCSayState",
            "Name": "\u89d2\u8272\u8bf4\u8bdd",
            "OwnerActorID": -1,
            "StartTime": 0.0,
            "EndTime": 1.0,
            "MinimalDuration": 0.1,
            "SoundFileName": "",
            "PlayFacialAnim": true
        },
        {
            "ClassPath": "NewRoco.Modules.System.Dialogue.Action.Timeline.DialogueTimelineNPCActorAnimAction",
            "Name": "\u52a8\u4f5c",
            "OwnerActorID": 33315,
            "StartTime": 0.0,
            "EndTime": 3.233,
            "MinimalDuration": 0.1,
            "Action": "Handreach",
            "BlendInTime": 0.5,
            "BlendOutTime": 0.5,
            "LoopCount": -1,
            "StartPoint": 0.0,
            "EndPoint": 0.0,
            "StopAnimAtEnd": false
        },
        {
            "ClassPath": "NewRoco.Modules.System.Dialogue.Action.Timeline.DialogueTimelineNPCActorAnimAction",
            "Name": "\u52a8\u4f5c",
            "OwnerActorID": -1,
            "StartTime": 3.0,
            "EndTime": 5.0,
            "MinimalDuration": 0.1,
            "Action": "PEmbarrass",
            "BlendInTime": 0.5,
            "BlendOutTime": 0.5,
            "LoopCount": -1,
            "StartPoint": 0.0,
            "EndPoint": 0.0,
            "StopAnimAtEnd": false,
            "Rate": 1
        },
        {
            "ClassPath": "NewRoco.Modules.System.Dialogue.Action.Timeline.DialogueTimelineNPCSetupAction",
            "Name": "\u671d\u5411",
            "OwnerActorID": 33315,
            "StartTime": 0.0,
            "BodyTargetActorID": 0,
            "BodyTurnTo": 0.0,
            "BodyTurnSpeedScale": 1.0,
            "HeadTargetActorID": 0,
            "HeadTurnTo": 300.0,
            "HeadTurnToY": -90.0,
            "HeadTurnSpeedScale": 1.0,
            "EyeTargetActorID": 0,
            "EyeTurnToHorizontal": 0.0,
            "EyeTurnToVertical": 0.0,
            "EyeTurnSpeedScale": 1.0
        },
        {
            "ClassPath": "NewRoco.Modules.System.Dialogue.Action.Timeline.DialogueTimelineNPCSetupAction",
            "Name": "\u671d\u5411",
            "OwnerActorID": -1,
            "StartTime": 0.0,
            "BodyTargetActorID": 0,
            "BodyTurnTo": 0.0,
            "BodyTurnSpeedScale": 1.0,
            "HeadTargetActorID": 35057,
            "HeadTurnTo": 0.0,
            "HeadTurnToY": 0.0,
            "HeadTurnSpeedScale": 1.0,
            "EyeTargetActorID": 0,
            "EyeTurnToHorizontal": 0.0,
            "EyeTurnToVertical": 0.0,
            "EyeTurnSpeedScale": 1.0
        },
        {
            "ClassPath": "NewRoco.Modules.System.Dialogue.Action.Timeline.DialogueTimelineCameraSetupEvent_FreeCamera",
            "Name": "\u81ea\u7531\u955c\u5934",
            "OwnerActorID": -101,
            "StartTime": 3.0,
            "EndTime": 6.0,
            "MinimalDuration": 0.1,
            "BlendType": 1,
            "BlendExp": 1.0,
            "TargetActorID": -6,
            "RelativeLocation": {
                "X": 90.6,
                "Y": 23.1,
                "Z": 130.0
            },
            "RelativeRotation": {
                "Pitch": 2.4,
                "Yaw": -30.8,
                "Roll": 0.0
            },
            "FOV": 45.0
        },
        {
            "ClassPath": "NewRoco.Modules.System.Dialogue.Action.Timeline.DialogueTimelineNPCSetupAction",
            "Name": "\u671d\u5411",
            "OwnerActorID": -1,
            "StartTime": 3.4,
            "BodyTargetActorID": 0,
            "BodyTurnTo": 0.0,
            "BodyTurnSpeedScale": 1.0,
            "HeadTargetActorID": 33315,
            "HeadTurnTo": 0.0,
            "HeadTurnToY": 0.0,
            "HeadTurnSpeedScale": 1.0,
            "EyeTargetActorID": 0,
            "EyeTurnToHorizontal": 0.0,
            "EyeTurnToVertical": 0.0,
            "EyeTurnSpeedScale": 1.0
        },
        {
            "ClassPath": "NewRoco.Modules.System.Dialogue.Action.Timeline.DialogueTimelineNPCSetLocationEvent",
            "Name": "\u8bbe\u7f6e\u4f4d\u7f6e",
            "OwnerActorID": 33315,
            "StartTime": 0.0,
            "TargetLocation": {
                "X": -48.5,
                "Y": -60.0,
                "Z": -3.0,
                "Base": "Mesh"
            },
            "TargetRotation": {
                "Pitch": 0.0,
                "Yaw": 0.0,
                "Roll": 0.0
            },
            "ReportLocation": false
        }
    ]
}