{
	"Desc": "团体战——技能表演机位",
	"TargetA": 1,
	"TargetB": 2,
	"SpringArmRotation":
	{
		"X": 0,
		"Y": 3,
		"Z": -30
	},
	"SpringArmOffset":
	{
		"X": 0,
		"Y": 130,
		"Z": -50
	},
	"SprintArmLength": 950,
	"CameraFov": 75,
	"EnableDepthOfField": false,
	"DepthOfFieldScale": 0,
	"ControllerArray": [
		{
			"IsEnable": true,
			"InputType": 2,
			"EffectType": 5,
			"Interval":
			{
				"X": 0,
				"Y": 100
			},
			"Desc": ""
		},
		{
			"IsEnable": true,
			"InputType": 3,
			"EffectType": 5,
			"Interval":
			{
				"X": 0,
				"Y": 150
			},
			"Desc": ""
		},
		{
			"IsEnable": true,
			"InputType": 3,
			"EffectType": 1,
			"Interval":
			{
				"X": 0,
				"Y": -3
			},
			"Desc": ""
		},
		{
			"IsEnable": true,
			"InputType": 3,
			"EffectType": 2,
			"Interval":
			{
				"X": 0,
				"Y": 4
			},
			"Desc": ""
		},
		{
			"IsEnable": true,
			"InputType": 3,
			"EffectType": 4,
			"Interval":
			{
				"X": 0,
				"Y": -50
			},
			"Desc": ""
		}
	]
}